smd/__init__.py
smd/_internals.py
smd/red.py
acrome_smd-2.0.6.dist-info/LICENSE
acrome_smd-2.0.6.dist-info/METADATA
acrome_smd-2.0.6.dist-info/WHEEL
acrome_smd-2.0.6.dist-info/top_level.txt
acrome_smd-2.0.6.dist-info/RECORD
