Metadata-Version: 2.1
Name: acrome-smd
Version: 2.0.6
Summary: Python library for interfacing with Acrome Smart Motion Devices (SMD) products.
Home-page: https://github.com/Acrome-Smart-Motion-Devices/python-library
Author: Furkan Kırlangıç
Author-email: furkankirlangic@acrome.net
Project-URL: Bug Tracker, https://github.com/Acrome-Smart-Motion-Devices/python-library/issues
Classifier: Programming Language :: Python :: 3
Classifier: License :: OSI Approved :: GNU General Public License v3 (GPLv3)
Classifier: Operating System :: OS Independent
Requires-Python: >=3.7
License-File: LICENSE
Requires-Dist: pyserial >=3.5
Requires-Dist: stm32loader >=0.5.1
Requires-Dist: crccheck >=1.3.0
Requires-Dist: requests >=2.31.0
Requires-Dist: packaging >=23.2
